oqi/__init__.py
oqi/oqi.py
oqi-1.0.3.dist-info/LICENSE
oqi-1.0.3.dist-info/METADATA
oqi-1.0.3.dist-info/WHEEL
oqi-1.0.3.dist-info/entry_points.txt
oqi-1.0.3.dist-info/top_level.txt
oqi-1.0.3.dist-info/RECORD
