Metadata-Version: 2.1
Name: oqi
Version: 1.0.3
Summary: Open Qasm interpreter.
Home-page: https://github.com/mentesniker/OpenQasmInterpreter
Author: Luis Mtz.
Author-email: mentesniker@gmail.com
License: MIT
Download-URL: https://pypi.org/project/oqi/
Keywords: OpenQasm,QuantumComputing,QuantumSimulator
Platform: UNKNOWN
Requires-Dist: qiskit (<0.23.5)
